orangecontrib/oranchada/__init__.py
orangecontrib/oranchada/base_widget/__init__.py
orangecontrib/oranchada/base_widget/arithmetic_widget.py
orangecontrib/oranchada/base_widget/base_widget.py
orangecontrib/oranchada/base_widget/creator_widget.py
orangecontrib/oranchada/base_widget/filter_widget.py
orangecontrib/oranchada/base_widget/types.py
orangecontrib/oranchada/processings/__init__.py
orangecontrib/oranchada/processings/add_baseline.py
orangecontrib/oranchada/processings/add_noise.py
orangecontrib/oranchada/processings/gen_spe.py
orangecontrib/oranchada/tests/__init__.py
orangecontrib/oranchada/tests/process_spectra_test.py
orangecontrib/oranchada/widgets_easy/__init__.py
orangecontrib/oranchada/widgets_easy/calibration_apply.py
orangecontrib/oranchada/widgets_easy/calibration_load.py
orangecontrib/oranchada/widgets_easy/gen_noisy_spe.py
orangecontrib/oranchada/widgets_easy/ploomber_base.py
orangecontrib/oranchada/widgets_easy/ploomber_import.py
orangecontrib/oranchada/widgets_easy/ploomber_twinning.py
orangecontrib/oranchada/widgets_easy/table2rcspectra.py
orangecontrib/oranchada/widgets_easy/xaxis_calibration.py
orangecontrib/oranchada/widgets_easy/yaxis_calibration.py
orangecontrib/oranchada/widgets_easy/icons/CHARISMA_logo.svg
orangecontrib/oranchada/widgets_easy/icons/cha.png
orangecontrib/oranchada/widgets_easy/icons/h5.png
orangecontrib/oranchada/widgets_easy/icons/nxs.png
orangecontrib/oranchada/widgets_easy/icons/ploomber.png
orangecontrib/oranchada/widgets_easy/icons/spectra.svg
orangecontrib/oranchada/widgets_easy/icons/twinning.png
orangecontrib/oranchada/widgets_easy/icons/upload.png
orangecontrib/oranchada/widgets_easy/ploomber/workflow_import/auth.py
orangecontrib/oranchada/widgets_easy/ploomber/workflow_import/createinvestigation.py
orangecontrib/oranchada/widgets_easy/ploomber/workflow_import/env_ploomber.yaml
orangecontrib/oranchada/widgets_easy/ploomber/workflow_import/generate_metadata.py
oranchada-1.0.1.dist-info/LICENSE
oranchada-1.0.1.dist-info/METADATA
oranchada-1.0.1.dist-info/WHEEL
oranchada-1.0.1.dist-info/entry_points.txt
oranchada-1.0.1.dist-info/top_level.txt
oranchada-1.0.1.dist-info/RECORD
