Metadata-Version: 2.1
Name: oranchada
Version: 1.0.1
Summary: Orange add-on for Raman spectroscopy
Home-page: https://github.com/h2020charisma/oranchada
Author: IDEAconsult Ltd.
Author-email: dev-charisma@ideaconsult.net
License: MIT
Keywords: Raman,oranchada,orange3 add-on,spectroscopy
Classifier: Development Status :: 5 - Production/Stable
Classifier: Environment :: Plugins
Classifier: Intended Audience :: Developers
Classifier: Intended Audience :: Education
Classifier: Intended Audience :: Science/Research
Classifier: License :: OSI Approved :: MIT License
Classifier: Operating System :: OS Independent
Classifier: Programming Language :: Python :: 3 :: Only
Classifier: Programming Language :: Python :: 3
Classifier: Programming Language :: Python
Classifier: Topic :: Scientific/Engineering :: Artificial Intelligence
Classifier: Topic :: Scientific/Engineering :: Bio-Informatics
Classifier: Topic :: Scientific/Engineering :: Visualization
Classifier: Topic :: Scientific/Engineering
Classifier: Topic :: Software Development :: Libraries :: Python Modules
Classifier: Topic :: Software Development :: Libraries
Requires-Python: >=3.9
License-File: LICENSE
Requires-Dist: Orange3 >=3.31.0
Requires-Dist: fuzzywuzzy ~=0.18.0
Requires-Dist: numpy >=1.18.0
Requires-Dist: orange-canvas-core >=0.1.24
Requires-Dist: orange-widget-base >=4.16.1
Requires-Dist: pip >=9.0
Requires-Dist: ploomber ~=0.23.0
Requires-Dist: ramanchada2 ==1.2.0
Requires-Dist: setuptools >=36.3
Requires-Dist: tables ~=3.9.1
Provides-Extra: test
Requires-Dist: coverage ; extra == 'test'
